<?xml version="1.0" encoding="UTF-8"?>
<mxfile host="app.diagrams.net" agent="Mozilla/5.0 (Windows NT 10.0; Win64; x64) AppleWebKit/537.36 (KHTML, like Gecko) Chrome/146.0.0.0 Safari/537.36" version="29.6.6">
  <diagram id="M1MUCiGryxHPwBPsW70c" name="DFD0">
    <mxGraphModel dx="696" dy="1622" grid="1" gridSize="10" guides="1" tooltips="1" connect="1" arrows="1" fold="1" page="0" pageScale="1" pageWidth="850" pageHeight="1100" math="0" shadow="0">
      <root>
        <mxCell id="0" />
        <mxCell id="1" parent="0" />
        <mxCell id="ysOjoahSiFBGGim9s-G7-128" edge="1" parent="1" source="ysOjoahSiFBGGim9s-G7-140" style="edgeStyle=orthogonalEdgeStyle;rounded=0;orthogonalLoop=1;jettySize=auto;html=1;entryX=0.048;entryY=0.712;entryDx=0;entryDy=0;fontSize=12;startSize=8;endSize=8;entryPerimeter=0;">
          <mxGeometry relative="1" as="geometry">
            <Array as="points">
              <mxPoint x="2210" y="667" />
            </Array>
            <mxPoint x="2193.28" y="972.7100000000002" as="sourcePoint" />
            <mxPoint x="2410" y="667.4300000000001" as="targetPoint" />
          </mxGeometry>
        </mxCell>
        <mxCell id="ysOjoahSiFBGGim9s-G7-129" connectable="0" parent="ysOjoahSiFBGGim9s-G7-128" style="edgeLabel;html=1;align=center;verticalAlign=middle;resizable=0;points=[];fontSize=12;" value="Kelola pemesanan" vertex="1">
          <mxGeometry relative="1" x="-0.4618" y="1" as="geometry">
            <mxPoint x="101" y="-172" as="offset" />
          </mxGeometry>
        </mxCell>
        <mxCell id="ysOjoahSiFBGGim9s-G7-132" edge="1" parent="1" source="ysOjoahSiFBGGim9s-G7-140" style="edgeStyle=orthogonalEdgeStyle;rounded=0;orthogonalLoop=1;jettySize=auto;html=1;entryX=0;entryY=1;entryDx=0;entryDy=0;fontSize=12;startSize=8;endSize=8;" target="ysOjoahSiFBGGim9s-G7-153">
          <mxGeometry relative="1" as="geometry">
            <Array as="points">
              <mxPoint x="2430" y="990" />
            </Array>
          </mxGeometry>
        </mxCell>
        <mxCell id="ysOjoahSiFBGGim9s-G7-133" connectable="0" parent="ysOjoahSiFBGGim9s-G7-132" style="edgeLabel;html=1;align=center;verticalAlign=middle;resizable=0;points=[];fontSize=12;" value="Kelola data paket dan portofolio" vertex="1">
          <mxGeometry relative="1" x="-0.5999" y="3" as="geometry">
            <mxPoint x="52" as="offset" />
          </mxGeometry>
        </mxCell>
        <mxCell id="ysOjoahSiFBGGim9s-G7-134" edge="1" parent="1" source="ysOjoahSiFBGGim9s-G7-140" style="edgeStyle=orthogonalEdgeStyle;rounded=0;orthogonalLoop=1;jettySize=auto;html=1;entryX=0;entryY=0;entryDx=0;entryDy=0;fontSize=12;startSize=8;endSize=8;" target="ysOjoahSiFBGGim9s-G7-180">
          <mxGeometry relative="1" as="geometry">
            <Array as="points">
              <mxPoint x="2250" y="1101" />
            </Array>
          </mxGeometry>
        </mxCell>
        <mxCell id="ysOjoahSiFBGGim9s-G7-135" connectable="0" parent="ysOjoahSiFBGGim9s-G7-134" style="edgeLabel;html=1;align=center;verticalAlign=middle;resizable=0;points=[];fontSize=12;" value="Verifikasi pembayaran" vertex="1">
          <mxGeometry relative="1" x="0.0291" y="-4" as="geometry">
            <mxPoint x="35" y="-4" as="offset" />
          </mxGeometry>
        </mxCell>
        <mxCell id="ysOjoahSiFBGGim9s-G7-136" edge="1" parent="1" source="ysOjoahSiFBGGim9s-G7-140" style="edgeStyle=orthogonalEdgeStyle;rounded=0;orthogonalLoop=1;jettySize=auto;html=1;entryX=0;entryY=0;entryDx=0;entryDy=0;fontSize=12;startSize=8;endSize=8;" target="ysOjoahSiFBGGim9s-G7-164">
          <mxGeometry relative="1" as="geometry">
            <Array as="points">
              <mxPoint x="2210" y="1281" />
            </Array>
          </mxGeometry>
        </mxCell>
        <mxCell id="ysOjoahSiFBGGim9s-G7-137" connectable="0" parent="ysOjoahSiFBGGim9s-G7-136" style="edgeLabel;html=1;align=center;verticalAlign=middle;resizable=0;points=[];fontSize=12;" value="Atur jadwal produksi" vertex="1">
          <mxGeometry relative="1" x="0.3273" as="geometry">
            <mxPoint x="33" as="offset" />
          </mxGeometry>
        </mxCell>
        <mxCell id="ysOjoahSiFBGGim9s-G7-138" edge="1" parent="1" source="ysOjoahSiFBGGim9s-G7-140" style="edgeStyle=orthogonalEdgeStyle;rounded=0;orthogonalLoop=1;jettySize=auto;html=1;entryX=0.028;entryY=0.358;entryDx=0;entryDy=0;fontSize=12;startSize=8;endSize=8;entryPerimeter=0;" target="ysOjoahSiFBGGim9s-G7-173">
          <mxGeometry relative="1" as="geometry">
            <Array as="points">
              <mxPoint x="2100" y="1000" />
              <mxPoint x="2100" y="1500" />
            </Array>
          </mxGeometry>
        </mxCell>
        <mxCell id="ysOjoahSiFBGGim9s-G7-139" connectable="0" parent="ysOjoahSiFBGGim9s-G7-138" style="edgeLabel;html=1;align=center;verticalAlign=middle;resizable=0;points=[];fontSize=12;" value="Permintaan laporan" vertex="1">
          <mxGeometry relative="1" x="0.5315" y="-2" as="geometry">
            <mxPoint x="6" y="-2" as="offset" />
          </mxGeometry>
        </mxCell>
        <mxCell id="ysOjoahSiFBGGim9s-G7-140" parent="1" style="rounded=0;whiteSpace=wrap;arcSize=50;strokeWidth=2;fixDash=0;" value="Admin" vertex="1">
          <mxGeometry height="40" width="120" x="2140" y="974.96" as="geometry" />
        </mxCell>
        <mxCell id="ysOjoahSiFBGGim9s-G7-143" parent="1" style="rounded=0;whiteSpace=wrap;arcSize=50;strokeWidth=2;fixDash=0;" value="Pelanggan" vertex="1">
          <mxGeometry height="40" width="120" x="2840" y="400" as="geometry" />
        </mxCell>
        <mxCell id="ysOjoahSiFBGGim9s-G7-144" parent="1" style="rounded=0;whiteSpace=wrap;arcSize=50;strokeWidth=2;fixDash=0;" value="Editor" vertex="1">
          <mxGeometry height="40" width="120" x="2120" y="1350" as="geometry" />
        </mxCell>
        <mxCell id="ysOjoahSiFBGGim9s-G7-147" edge="1" parent="1" source="ysOjoahSiFBGGim9s-G7-153" style="edgeStyle=orthogonalEdgeStyle;rounded=0;orthogonalLoop=1;jettySize=auto;html=1;entryX=0.75;entryY=0;entryDx=0;entryDy=0;fontSize=12;startSize=8;endSize=8;" target="ysOjoahSiFBGGim9s-G7-140">
          <mxGeometry relative="1" as="geometry">
            <Array as="points">
              <mxPoint x="2230" y="880" />
            </Array>
          </mxGeometry>
        </mxCell>
        <mxCell id="ysOjoahSiFBGGim9s-G7-148" connectable="0" parent="ysOjoahSiFBGGim9s-G7-147" style="edgeLabel;html=1;align=center;verticalAlign=middle;resizable=0;points=[];fontSize=12;" value="Data paket dan portofolio" vertex="1">
          <mxGeometry relative="1" x="-0.023" as="geometry">
            <mxPoint x="43" as="offset" />
          </mxGeometry>
        </mxCell>
        <mxCell id="ysOjoahSiFBGGim9s-G7-153" parent="1" style="ellipse;aspect=fixed;strokeWidth=2;whiteSpace=wrap;fixDash=0;" value="P3.0&#xa;Kelola Paket &amp; &#xa;Portofolio" vertex="1">
          <mxGeometry height="140" width="140" x="2410" y="800" as="geometry" />
        </mxCell>
        <mxCell id="ysOjoahSiFBGGim9s-G7-154" edge="1" parent="1" source="ysOjoahSiFBGGim9s-G7-164" style="edgeStyle=orthogonalEdgeStyle;rounded=0;orthogonalLoop=1;jettySize=auto;html=1;entryX=0.418;entryY=1.022;entryDx=0;entryDy=0;fontSize=12;startSize=8;endSize=8;entryPerimeter=0;" target="ysOjoahSiFBGGim9s-G7-140">
          <mxGeometry relative="1" as="geometry">
            <Array as="points">
              <mxPoint x="2190" y="1300" />
            </Array>
          </mxGeometry>
        </mxCell>
        <mxCell id="ysOjoahSiFBGGim9s-G7-155" connectable="0" parent="ysOjoahSiFBGGim9s-G7-154" style="edgeLabel;html=1;align=center;verticalAlign=middle;resizable=0;points=[];fontSize=12;" value="Informasi jadwal dan progres produksi" vertex="1">
          <mxGeometry relative="1" x="-0.4164" y="-1" as="geometry">
            <mxPoint x="32" as="offset" />
          </mxGeometry>
        </mxCell>
        <mxCell id="ysOjoahSiFBGGim9s-G7-156" edge="1" parent="1" source="ysOjoahSiFBGGim9s-G7-164" style="edgeStyle=orthogonalEdgeStyle;rounded=0;orthogonalLoop=1;jettySize=auto;html=1;entryX=0.5;entryY=0;entryDx=0;entryDy=0;fontSize=12;startSize=8;endSize=8;" target="ysOjoahSiFBGGim9s-G7-144">
          <mxGeometry relative="1" as="geometry" />
        </mxCell>
        <mxCell id="ysOjoahSiFBGGim9s-G7-157" connectable="0" parent="ysOjoahSiFBGGim9s-G7-156" style="edgeLabel;html=1;align=center;verticalAlign=middle;resizable=0;points=[];fontSize=12;" value="Daftar tugas editing dan jadwal produksi" vertex="1">
          <mxGeometry relative="1" x="0.2217" y="3" as="geometry">
            <mxPoint x="33" y="-3" as="offset" />
          </mxGeometry>
        </mxCell>
        <mxCell id="ysOjoahSiFBGGim9s-G7-158" edge="1" parent="1" source="ysOjoahSiFBGGim9s-G7-164" style="edgeStyle=orthogonalEdgeStyle;rounded=0;orthogonalLoop=1;jettySize=auto;html=1;entryX=0.5;entryY=1;entryDx=0;entryDy=0;fontSize=12;startSize=8;endSize=8;" target="ysOjoahSiFBGGim9s-G7-199">
          <mxGeometry relative="1" as="geometry">
            <Array as="points">
              <mxPoint x="2980" y="1310" />
            </Array>
          </mxGeometry>
        </mxCell>
        <mxCell id="ysOjoahSiFBGGim9s-G7-159" connectable="0" parent="ysOjoahSiFBGGim9s-G7-158" style="edgeLabel;html=1;align=center;verticalAlign=middle;resizable=0;points=[];fontSize=12;" value="Update status pemesanan" vertex="1">
          <mxGeometry relative="1" x="-0.7273" y="1" as="geometry">
            <mxPoint x="34" as="offset" />
          </mxGeometry>
        </mxCell>
        <mxCell id="ysOjoahSiFBGGim9s-G7-162" edge="1" parent="1" source="ysOjoahSiFBGGim9s-G7-164" style="edgeStyle=orthogonalEdgeStyle;rounded=0;orthogonalLoop=1;jettySize=auto;html=1;entryX=0.5;entryY=0;entryDx=0;entryDy=0;fontSize=12;startSize=8;endSize=8;exitX=0.923;exitY=0.79;exitDx=0;exitDy=0;exitPerimeter=0;">
          <mxGeometry relative="1" as="geometry">
            <Array as="points">
              <mxPoint x="2783" y="1371" />
            </Array>
            <mxPoint x="2560.000805493628" y="1369.9112765957448" as="sourcePoint" />
            <mxPoint x="2782.57" y="1409.9996641535297" as="targetPoint" />
          </mxGeometry>
        </mxCell>
        <mxCell id="ysOjoahSiFBGGim9s-G7-163" connectable="0" parent="ysOjoahSiFBGGim9s-G7-162" style="edgeLabel;html=1;align=center;verticalAlign=middle;resizable=0;points=[];fontSize=12;" value="Data jadwal produksi baru/ubah" vertex="1">
          <mxGeometry relative="1" x="-0.2749" y="1" as="geometry">
            <mxPoint x="17" y="1" as="offset" />
          </mxGeometry>
        </mxCell>
        <mxCell id="ysOjoahSiFBGGim9s-G7-164" parent="1" style="ellipse;aspect=fixed;strokeWidth=2;whiteSpace=wrap;fixDash=0;" value="P5.0&#xa;Penjadwalan Produksi dan&#xa;Progres Editing" vertex="1">
          <mxGeometry height="140" width="140" x="2410" y="1260" as="geometry" />
        </mxCell>
        <mxCell id="ysOjoahSiFBGGim9s-G7-165" edge="1" parent="1" source="ysOjoahSiFBGGim9s-G7-173" style="edgeStyle=orthogonalEdgeStyle;rounded=0;orthogonalLoop=1;jettySize=auto;html=1;entryX=0;entryY=0.25;entryDx=0;entryDy=0;fontSize=12;startSize=8;endSize=8;" target="ysOjoahSiFBGGim9s-G7-140">
          <mxGeometry relative="1" as="geometry">
            <Array as="points">
              <mxPoint x="2080" y="1520" />
              <mxPoint x="2080" y="985" />
            </Array>
          </mxGeometry>
        </mxCell>
        <mxCell id="ysOjoahSiFBGGim9s-G7-166" connectable="0" parent="ysOjoahSiFBGGim9s-G7-165" style="edgeLabel;html=1;align=center;verticalAlign=middle;resizable=0;points=[];fontSize=12;" value="Laporan pemesanan, pendapatan dan pengeluaran" vertex="1">
          <mxGeometry relative="1" x="-0.511" as="geometry">
            <mxPoint x="56" as="offset" />
          </mxGeometry>
        </mxCell>
        <mxCell id="ysOjoahSiFBGGim9s-G7-167" edge="1" parent="1" source="ysOjoahSiFBGGim9s-G7-173" style="edgeStyle=orthogonalEdgeStyle;rounded=0;orthogonalLoop=1;jettySize=auto;html=1;fontSize=12;startSize=8;endSize=8;jumpStyle=arc;">
          <mxGeometry relative="1" as="geometry">
            <Array as="points">
              <mxPoint x="3050" y="1540" />
            </Array>
            <mxPoint x="3050" y="940" as="targetPoint" />
          </mxGeometry>
        </mxCell>
        <mxCell id="ysOjoahSiFBGGim9s-G7-168" connectable="0" parent="ysOjoahSiFBGGim9s-G7-167" style="edgeLabel;html=1;align=center;verticalAlign=middle;resizable=0;points=[];fontSize=12;" value="Permintaan data pemesanan" vertex="1">
          <mxGeometry relative="1" x="-0.8206" y="-2" as="geometry">
            <mxPoint x="174" as="offset" />
          </mxGeometry>
        </mxCell>
        <mxCell id="ysOjoahSiFBGGim9s-G7-169" edge="1" parent="1" source="ysOjoahSiFBGGim9s-G7-173" style="edgeStyle=orthogonalEdgeStyle;rounded=0;orthogonalLoop=1;jettySize=auto;html=1;entryX=0;entryY=0.25;entryDx=0;entryDy=0;fontSize=12;startSize=8;endSize=8;" target="ysOjoahSiFBGGim9s-G7-214">
          <mxGeometry relative="1" as="geometry">
            <Array as="points">
              <mxPoint x="2480" y="1420" />
            </Array>
          </mxGeometry>
        </mxCell>
        <mxCell id="ysOjoahSiFBGGim9s-G7-170" connectable="0" parent="ysOjoahSiFBGGim9s-G7-169" style="edgeLabel;html=1;align=center;verticalAlign=middle;resizable=0;points=[];fontSize=12;" value="Permintaan data jadwal produksi" vertex="1">
          <mxGeometry relative="1" x="-0.0137" y="-3" as="geometry">
            <mxPoint x="6" y="-3" as="offset" />
          </mxGeometry>
        </mxCell>
        <mxCell id="ysOjoahSiFBGGim9s-G7-171" edge="1" parent="1" source="ysOjoahSiFBGGim9s-G7-173" style="edgeStyle=orthogonalEdgeStyle;rounded=0;orthogonalLoop=1;jettySize=auto;html=1;entryX=0;entryY=0.5;entryDx=0;entryDy=0;" target="ysOjoahSiFBGGim9s-G7-249">
          <mxGeometry relative="1" as="geometry">
            <Array as="points">
              <mxPoint x="2480" y="1600" />
            </Array>
          </mxGeometry>
        </mxCell>
        <mxCell id="ysOjoahSiFBGGim9s-G7-172" connectable="0" parent="ysOjoahSiFBGGim9s-G7-171" style="edgeLabel;html=1;align=center;verticalAlign=middle;resizable=0;points=[];" value="Simpan pengeluaran" vertex="1">
          <mxGeometry relative="1" x="-0.1102" y="-1" as="geometry">
            <mxPoint as="offset" />
          </mxGeometry>
        </mxCell>
        <mxCell id="ysOjoahSiFBGGim9s-G7-173" parent="1" style="ellipse;aspect=fixed;strokeWidth=2;whiteSpace=wrap;fixDash=0;" value="P6.0&#xa;Pelaporan" vertex="1">
          <mxGeometry height="140" width="140" x="2410" y="1450" as="geometry" />
        </mxCell>
        <mxCell id="ysOjoahSiFBGGim9s-G7-174" edge="1" parent="1" source="ysOjoahSiFBGGim9s-G7-180" style="edgeStyle=orthogonalEdgeStyle;rounded=0;orthogonalLoop=1;jettySize=auto;html=1;fontSize=12;startSize=8;endSize=8;exitX=0.93;exitY=0.211;exitDx=0;exitDy=0;exitPerimeter=0;">
          <mxGeometry relative="1" as="geometry">
            <Array as="points">
              <mxPoint x="2540" y="1110" />
              <mxPoint x="2930" y="1110" />
            </Array>
            <mxPoint x="2930" y="940" as="targetPoint" />
          </mxGeometry>
        </mxCell>
        <mxCell id="ysOjoahSiFBGGim9s-G7-175" connectable="0" parent="ysOjoahSiFBGGim9s-G7-174" style="edgeLabel;html=1;align=center;verticalAlign=middle;resizable=0;points=[];fontSize=12;" value="Update status pembayaran" vertex="1">
          <mxGeometry relative="1" x="-0.5353" y="1" as="geometry">
            <mxPoint x="60" as="offset" />
          </mxGeometry>
        </mxCell>
        <mxCell id="ysOjoahSiFBGGim9s-G7-176" edge="1" parent="1" source="ysOjoahSiFBGGim9s-G7-180" style="edgeStyle=orthogonalEdgeStyle;rounded=0;orthogonalLoop=1;jettySize=auto;html=1;entryX=0.5;entryY=0;entryDx=0;entryDy=0;fontSize=12;startSize=8;endSize=8;" target="ysOjoahSiFBGGim9s-G7-208">
          <mxGeometry relative="1" as="geometry">
            <Array as="points">
              <mxPoint x="2860" y="1170" />
            </Array>
          </mxGeometry>
        </mxCell>
        <mxCell id="ysOjoahSiFBGGim9s-G7-177" connectable="0" parent="ysOjoahSiFBGGim9s-G7-176" style="edgeLabel;html=1;align=center;verticalAlign=middle;resizable=0;points=[];fontSize=12;" value="Data pembayaran baru/ubah" vertex="1">
          <mxGeometry relative="1" x="-0.6494" y="-1" as="geometry">
            <mxPoint x="51" y="-2" as="offset" />
          </mxGeometry>
        </mxCell>
        <mxCell id="ysOjoahSiFBGGim9s-G7-178" edge="1" parent="1" source="ysOjoahSiFBGGim9s-G7-180" style="edgeStyle=orthogonalEdgeStyle;rounded=0;orthogonalLoop=1;jettySize=auto;html=1;entryX=0.75;entryY=1;entryDx=0;entryDy=0;fontSize=12;startSize=8;endSize=8;" target="ysOjoahSiFBGGim9s-G7-140">
          <mxGeometry relative="1" as="geometry" />
        </mxCell>
        <mxCell id="ysOjoahSiFBGGim9s-G7-179" connectable="0" parent="ysOjoahSiFBGGim9s-G7-178" style="edgeLabel;html=1;align=center;verticalAlign=middle;resizable=0;points=[];fontSize=12;" value="Data pembayaran" vertex="1">
          <mxGeometry relative="1" x="-0.1486" y="1" as="geometry">
            <mxPoint x="58" y="-1" as="offset" />
          </mxGeometry>
        </mxCell>
        <mxCell id="ysOjoahSiFBGGim9s-G7-180" parent="1" style="ellipse;aspect=fixed;strokeWidth=2;whiteSpace=wrap;fixDash=0;" value="P4.0&#xa;Kelola Pembayaran" vertex="1">
          <mxGeometry height="140" width="140" x="2410" y="1080" as="geometry" />
        </mxCell>
        <mxCell id="ysOjoahSiFBGGim9s-G7-181" edge="1" parent="1" source="mm8ewPxjDXuYCMIWR43z-1" style="edgeStyle=orthogonalEdgeStyle;rounded=0;orthogonalLoop=1;jettySize=auto;html=1;fontSize=12;startSize=8;endSize=8;exitX=0.074;exitY=0.215;exitDx=0;exitDy=0;exitPerimeter=0;" target="ysOjoahSiFBGGim9s-G7-140">
          <mxGeometry relative="1" as="geometry">
            <Array as="points">
              <mxPoint x="2190" y="620" />
            </Array>
            <mxPoint x="2410" y="660.86" as="sourcePoint" />
            <mxPoint x="2165.52" y="974.9600000000002" as="targetPoint" />
          </mxGeometry>
        </mxCell>
        <mxCell id="ysOjoahSiFBGGim9s-G7-182" connectable="0" parent="ysOjoahSiFBGGim9s-G7-181" style="edgeLabel;html=1;align=center;verticalAlign=middle;resizable=0;points=[];fontSize=12;" value="Data pemesanan" vertex="1">
          <mxGeometry relative="1" x="0.2369" y="-1" as="geometry">
            <mxPoint x="121" y="-132" as="offset" />
          </mxGeometry>
        </mxCell>
        <mxCell id="ysOjoahSiFBGGim9s-G7-187" parent="1" style="ellipse;aspect=fixed;strokeWidth=2;whiteSpace=wrap;fixDash=0;" value="P1.0&#xa;Kelola User" vertex="1">
          <mxGeometry height="140" width="140" x="2410" y="370" as="geometry" />
        </mxCell>
        <mxCell id="ysOjoahSiFBGGim9s-G7-198" connectable="0" parent="1" style="group;" value="" vertex="1">
          <mxGeometry height="30.08" width="160" x="2900" y="909.9200000000001" as="geometry" />
        </mxCell>
        <mxCell id="ysOjoahSiFBGGim9s-G7-199" parent="ysOjoahSiFBGGim9s-G7-198" style="text;html=1;whiteSpace=wrap;strokeColor=none;fillColor=none;align=center;verticalAlign=middle;rounded=0;fontSize=16;" value="D4 TB_PEMESANAN" vertex="1">
          <mxGeometry height="29.997532556545664" width="160" y="0.08246744345433552" as="geometry" />
        </mxCell>
        <mxCell id="ysOjoahSiFBGGim9s-G7-200" edge="1" parent="ysOjoahSiFBGGim9s-G7-198" style="endArrow=none;html=1;rounded=0;fontSize=12;startSize=8;endSize=8;curved=1;" value="">
          <mxGeometry height="50" relative="1" width="50" as="geometry">
            <mxPoint as="sourcePoint" />
            <mxPoint x="160" as="targetPoint" />
          </mxGeometry>
        </mxCell>
        <mxCell id="ysOjoahSiFBGGim9s-G7-201" edge="1" parent="ysOjoahSiFBGGim9s-G7-198" style="endArrow=none;html=1;rounded=0;fontSize=12;startSize=8;endSize=8;curved=1;" value="">
          <mxGeometry height="50" relative="1" width="50" as="geometry">
            <mxPoint y="30" as="sourcePoint" />
            <mxPoint x="160" y="30" as="targetPoint" />
          </mxGeometry>
        </mxCell>
        <mxCell id="ysOjoahSiFBGGim9s-G7-202" edge="1" parent="ysOjoahSiFBGGim9s-G7-198" source="ysOjoahSiFBGGim9s-G7-199" style="edgeStyle=none;curved=1;rounded=0;orthogonalLoop=1;jettySize=auto;html=1;exitX=0.5;exitY=0;exitDx=0;exitDy=0;fontSize=12;startSize=8;endSize=8;">
          <mxGeometry relative="1" as="geometry">
            <mxPoint x="80" as="targetPoint" />
          </mxGeometry>
        </mxCell>
        <mxCell id="ysOjoahSiFBGGim9s-G7-207" connectable="0" parent="1" style="group;" value="" vertex="1">
          <mxGeometry height="30.08" width="180" x="2770" y="1220" as="geometry" />
        </mxCell>
        <mxCell id="ysOjoahSiFBGGim9s-G7-208" parent="ysOjoahSiFBGGim9s-G7-207" style="text;html=1;whiteSpace=wrap;strokeColor=none;fillColor=none;align=center;verticalAlign=middle;rounded=0;fontSize=16;" value="D5 TB_PEMBAYARAN" vertex="1">
          <mxGeometry height="29.997532556545664" width="180" y="0.08246744345433552" as="geometry" />
        </mxCell>
        <mxCell id="ysOjoahSiFBGGim9s-G7-209" edge="1" parent="ysOjoahSiFBGGim9s-G7-207" style="endArrow=none;html=1;rounded=0;fontSize=12;startSize=8;endSize=8;curved=1;" value="">
          <mxGeometry height="50" relative="1" width="50" as="geometry">
            <mxPoint as="sourcePoint" />
            <mxPoint x="180" as="targetPoint" />
          </mxGeometry>
        </mxCell>
        <mxCell id="ysOjoahSiFBGGim9s-G7-210" edge="1" parent="ysOjoahSiFBGGim9s-G7-207" style="endArrow=none;html=1;rounded=0;fontSize=12;startSize=8;endSize=8;curved=1;" value="">
          <mxGeometry height="50" relative="1" width="50" as="geometry">
            <mxPoint y="30" as="sourcePoint" />
            <mxPoint x="180" y="30" as="targetPoint" />
          </mxGeometry>
        </mxCell>
        <mxCell id="ysOjoahSiFBGGim9s-G7-211" edge="1" parent="ysOjoahSiFBGGim9s-G7-207" source="ysOjoahSiFBGGim9s-G7-208" style="edgeStyle=none;curved=1;rounded=0;orthogonalLoop=1;jettySize=auto;html=1;exitX=0.5;exitY=0;exitDx=0;exitDy=0;fontSize=12;startSize=8;endSize=8;">
          <mxGeometry relative="1" as="geometry">
            <mxPoint x="90" as="targetPoint" />
          </mxGeometry>
        </mxCell>
        <mxCell id="ysOjoahSiFBGGim9s-G7-212" edge="1" parent="ysOjoahSiFBGGim9s-G7-207" source="ysOjoahSiFBGGim9s-G7-208" style="edgeStyle=none;curved=1;rounded=0;orthogonalLoop=1;jettySize=auto;html=1;exitX=0.5;exitY=1;exitDx=0;exitDy=0;fontSize=12;startSize=8;endSize=8;" target="ysOjoahSiFBGGim9s-G7-208">
          <mxGeometry relative="1" as="geometry" />
        </mxCell>
        <mxCell id="ysOjoahSiFBGGim9s-G7-213" connectable="0" parent="1" style="group;" value="" vertex="1">
          <mxGeometry height="40" width="140" x="2690" y="1410" as="geometry" />
        </mxCell>
        <mxCell id="ysOjoahSiFBGGim9s-G7-214" parent="ysOjoahSiFBGGim9s-G7-213" style="text;html=1;whiteSpace=wrap;strokeColor=none;fillColor=none;align=center;verticalAlign=middle;rounded=0;fontSize=16;" value="D6 TB_JADWAL" vertex="1">
          <mxGeometry height="39.8903358464703" width="140" y="0.10966415352970148" as="geometry" />
        </mxCell>
        <mxCell id="ysOjoahSiFBGGim9s-G7-215" edge="1" parent="ysOjoahSiFBGGim9s-G7-213" style="endArrow=none;html=1;rounded=0;fontSize=12;startSize=8;endSize=8;curved=1;entryX=1;entryY=0;entryDx=0;entryDy=0;" target="ysOjoahSiFBGGim9s-G7-214" value="">
          <mxGeometry height="50" relative="1" width="50" as="geometry">
            <mxPoint y="0.10966415352970148" as="sourcePoint" />
            <mxPoint x="104.99999999999999" y="0.10966415352970148" as="targetPoint" />
          </mxGeometry>
        </mxCell>
        <mxCell id="ysOjoahSiFBGGim9s-G7-216" edge="1" parent="ysOjoahSiFBGGim9s-G7-213" style="endArrow=none;html=1;rounded=0;fontSize=12;startSize=8;endSize=8;curved=1;entryX=1;entryY=1;entryDx=0;entryDy=0;" target="ysOjoahSiFBGGim9s-G7-214" value="">
          <mxGeometry height="50" relative="1" width="50" as="geometry">
            <mxPoint y="40" as="sourcePoint" />
            <mxPoint x="104.99999999999999" y="40" as="targetPoint" />
          </mxGeometry>
        </mxCell>
        <mxCell id="ysOjoahSiFBGGim9s-G7-217" edge="1" parent="ysOjoahSiFBGGim9s-G7-213" source="ysOjoahSiFBGGim9s-G7-214" style="edgeStyle=none;curved=1;rounded=0;orthogonalLoop=1;jettySize=auto;html=1;exitX=0.5;exitY=0;exitDx=0;exitDy=0;fontSize=12;startSize=8;endSize=8;">
          <mxGeometry relative="1" as="geometry">
            <mxPoint x="70" as="targetPoint" />
          </mxGeometry>
        </mxCell>
        <mxCell id="ysOjoahSiFBGGim9s-G7-226" edge="1" parent="1" source="ysOjoahSiFBGGim9s-G7-199" style="edgeStyle=orthogonalEdgeStyle;rounded=0;orthogonalLoop=1;jettySize=auto;html=1;fontSize=12;startSize=8;endSize=8;">
          <mxGeometry relative="1" as="geometry">
            <Array as="points">
              <mxPoint x="2950" y="1140" />
            </Array>
            <mxPoint x="2550" y="1140" as="targetPoint" />
          </mxGeometry>
        </mxCell>
        <mxCell id="ysOjoahSiFBGGim9s-G7-227" connectable="0" parent="ysOjoahSiFBGGim9s-G7-226" style="edgeLabel;html=1;align=center;verticalAlign=middle;resizable=0;points=[];fontSize=12;" value="Data pemesanan terkait" vertex="1">
          <mxGeometry relative="1" x="0.5333" y="2" as="geometry">
            <mxPoint x="40" y="-2" as="offset" />
          </mxGeometry>
        </mxCell>
        <mxCell id="ysOjoahSiFBGGim9s-G7-228" edge="1" parent="1" source="ysOjoahSiFBGGim9s-G7-208" style="edgeStyle=orthogonalEdgeStyle;rounded=0;orthogonalLoop=1;jettySize=auto;html=1;entryX=1;entryY=1;entryDx=0;entryDy=0;fontSize=12;startSize=8;endSize=8;" target="ysOjoahSiFBGGim9s-G7-180">
          <mxGeometry relative="1" as="geometry">
            <Array as="points">
              <mxPoint x="2800" y="1200" />
              <mxPoint x="2730" y="1200" />
            </Array>
          </mxGeometry>
        </mxCell>
        <mxCell id="ysOjoahSiFBGGim9s-G7-229" connectable="0" parent="ysOjoahSiFBGGim9s-G7-228" style="edgeLabel;html=1;align=center;verticalAlign=middle;resizable=0;points=[];fontSize=12;" value="Data pembayaran" vertex="1">
          <mxGeometry relative="1" x="0.6782" y="-1" as="geometry">
            <mxPoint x="67" y="-1" as="offset" />
          </mxGeometry>
        </mxCell>
        <mxCell id="ysOjoahSiFBGGim9s-G7-234" edge="1" parent="1" source="ysOjoahSiFBGGim9s-G7-144" style="edgeStyle=orthogonalEdgeStyle;rounded=0;orthogonalLoop=1;jettySize=auto;html=1;entryX=0;entryY=1;entryDx=0;entryDy=0;fontSize=12;startSize=8;endSize=8;" target="ysOjoahSiFBGGim9s-G7-164">
          <mxGeometry relative="1" as="geometry">
            <Array as="points">
              <mxPoint x="2180" y="1410" />
              <mxPoint x="2430" y="1410" />
              <mxPoint x="2430" y="1380" />
            </Array>
          </mxGeometry>
        </mxCell>
        <mxCell id="ysOjoahSiFBGGim9s-G7-235" connectable="0" parent="ysOjoahSiFBGGim9s-G7-234" style="edgeLabel;html=1;align=center;verticalAlign=middle;resizable=0;points=[];fontSize=12;" value="Login editor dan update progres editing" vertex="1">
          <mxGeometry relative="1" x="-0.2712" y="2" as="geometry">
            <mxPoint x="27" as="offset" />
          </mxGeometry>
        </mxCell>
        <mxCell id="ysOjoahSiFBGGim9s-G7-236" edge="1" parent="1" source="ysOjoahSiFBGGim9s-G7-199" style="edgeStyle=orthogonalEdgeStyle;rounded=0;orthogonalLoop=1;jettySize=auto;html=1;entryX=1;entryY=0.5;entryDx=0;entryDy=0;fontSize=12;startSize=8;endSize=8;" target="ysOjoahSiFBGGim9s-G7-164">
          <mxGeometry relative="1" as="geometry">
            <Array as="points">
              <mxPoint x="3010" y="1330" />
            </Array>
          </mxGeometry>
        </mxCell>
        <mxCell id="ysOjoahSiFBGGim9s-G7-237" connectable="0" parent="ysOjoahSiFBGGim9s-G7-236" style="edgeLabel;html=1;align=center;verticalAlign=middle;resizable=0;points=[];fontSize=12;" value="Data pemesanan untuk dijadwalkan" vertex="1">
          <mxGeometry relative="1" x="0.7593" y="2" as="geometry">
            <mxPoint x="58" y="-2" as="offset" />
          </mxGeometry>
        </mxCell>
        <mxCell id="ysOjoahSiFBGGim9s-G7-238" edge="1" parent="1" source="ysOjoahSiFBGGim9s-G7-214" style="edgeStyle=orthogonalEdgeStyle;rounded=0;orthogonalLoop=1;jettySize=auto;html=1;entryX=0.785;entryY=0.922;entryDx=0;entryDy=0;fontSize=12;startSize=8;endSize=8;entryPerimeter=0;" target="ysOjoahSiFBGGim9s-G7-164">
          <mxGeometry relative="1" as="geometry">
            <Array as="points">
              <mxPoint x="2750" y="1390" />
              <mxPoint x="2520" y="1390" />
            </Array>
          </mxGeometry>
        </mxCell>
        <mxCell id="ysOjoahSiFBGGim9s-G7-239" connectable="0" parent="ysOjoahSiFBGGim9s-G7-238" style="edgeLabel;html=1;align=center;verticalAlign=middle;resizable=0;points=[];fontSize=12;" value="Data jadwal dan status produksi" vertex="1">
          <mxGeometry relative="1" x="0.5468" y="-1" as="geometry">
            <mxPoint x="74" y="1" as="offset" />
          </mxGeometry>
        </mxCell>
        <mxCell id="ysOjoahSiFBGGim9s-G7-240" edge="1" parent="1" style="edgeStyle=orthogonalEdgeStyle;rounded=0;orthogonalLoop=1;jettySize=auto;html=1;entryX=1;entryY=0.5;entryDx=0;entryDy=0;fontSize=12;startSize=8;endSize=8;jumpStyle=arc;" target="ysOjoahSiFBGGim9s-G7-173">
          <mxGeometry relative="1" as="geometry">
            <Array as="points">
              <mxPoint x="3030" y="1520" />
            </Array>
            <mxPoint x="3030" y="940" as="sourcePoint" />
          </mxGeometry>
        </mxCell>
        <mxCell id="ysOjoahSiFBGGim9s-G7-241" connectable="0" parent="ysOjoahSiFBGGim9s-G7-240" style="edgeLabel;html=1;align=center;verticalAlign=middle;resizable=0;points=[];fontSize=12;" value="Data pemesanan" vertex="1">
          <mxGeometry relative="1" x="0.7491" y="5" as="geometry">
            <mxPoint x="127" y="-5" as="offset" />
          </mxGeometry>
        </mxCell>
        <mxCell id="ysOjoahSiFBGGim9s-G7-242" edge="1" parent="1" source="ysOjoahSiFBGGim9s-G7-208" style="edgeStyle=orthogonalEdgeStyle;rounded=0;orthogonalLoop=1;jettySize=auto;html=1;entryX=0.973;entryY=0.311;entryDx=0;entryDy=0;entryPerimeter=0;fontSize=12;startSize=8;endSize=8;jumpStyle=arc;" target="ysOjoahSiFBGGim9s-G7-173">
          <mxGeometry relative="1" as="geometry">
            <Array as="points">
              <mxPoint x="2910" y="1494" />
              <mxPoint x="2546" y="1494" />
            </Array>
          </mxGeometry>
        </mxCell>
        <mxCell id="ysOjoahSiFBGGim9s-G7-243" connectable="0" parent="ysOjoahSiFBGGim9s-G7-242" style="edgeLabel;html=1;align=center;verticalAlign=middle;resizable=0;points=[];fontSize=12;" value="Data pembayaran" vertex="1">
          <mxGeometry relative="1" x="0.5819" as="geometry">
            <mxPoint x="64" as="offset" />
          </mxGeometry>
        </mxCell>
        <mxCell id="ysOjoahSiFBGGim9s-G7-244" edge="1" parent="1" source="ysOjoahSiFBGGim9s-G7-173" style="edgeStyle=orthogonalEdgeStyle;rounded=0;orthogonalLoop=1;jettySize=auto;html=1;entryX=0.5;entryY=1;entryDx=0;entryDy=0;fontSize=12;startSize=8;endSize=8;jumpStyle=arc;" target="ysOjoahSiFBGGim9s-G7-208">
          <mxGeometry relative="1" as="geometry">
            <Array as="points">
              <mxPoint x="2860" y="1470" />
            </Array>
          </mxGeometry>
        </mxCell>
        <mxCell id="ysOjoahSiFBGGim9s-G7-245" connectable="0" parent="ysOjoahSiFBGGim9s-G7-244" style="edgeLabel;html=1;align=center;verticalAlign=middle;resizable=0;points=[];fontSize=12;" value="Permintaan data&amp;nbsp;&lt;span style=&quot;background-color: light-dark(#ffffff, var(--ge-dark-color, #121212)); color: light-dark(rgb(0, 0, 0), rgb(255, 255, 255));&quot;&gt;pembayaran&lt;/span&gt;" vertex="1">
          <mxGeometry relative="1" x="-0.5446" y="-1" as="geometry">
            <mxPoint x="60" y="-1" as="offset" />
          </mxGeometry>
        </mxCell>
        <mxCell id="ysOjoahSiFBGGim9s-G7-246" edge="1" parent="1" source="ysOjoahSiFBGGim9s-G7-214" style="edgeStyle=orthogonalEdgeStyle;rounded=0;orthogonalLoop=1;jettySize=auto;html=1;entryX=0.732;entryY=0.051;entryDx=0;entryDy=0;entryPerimeter=0;fontSize=12;startSize=8;endSize=8;" target="ysOjoahSiFBGGim9s-G7-173">
          <mxGeometry relative="1" as="geometry">
            <Array as="points">
              <mxPoint x="2513" y="1440" />
            </Array>
          </mxGeometry>
        </mxCell>
        <mxCell id="ysOjoahSiFBGGim9s-G7-247" connectable="0" parent="ysOjoahSiFBGGim9s-G7-246" style="edgeLabel;html=1;align=center;verticalAlign=middle;resizable=0;points=[];fontSize=12;" value="Data jadwal produksi" vertex="1">
          <mxGeometry relative="1" x="0.3105" y="1" as="geometry">
            <mxPoint x="28" as="offset" />
          </mxGeometry>
        </mxCell>
        <mxCell id="ysOjoahSiFBGGim9s-G7-248" connectable="0" parent="1" style="group;" value="" vertex="1">
          <mxGeometry height="40" width="320" x="2700" y="1580" as="geometry" />
        </mxCell>
        <mxCell id="ysOjoahSiFBGGim9s-G7-249" parent="ysOjoahSiFBGGim9s-G7-248" style="text;html=1;whiteSpace=wrap;strokeColor=none;fillColor=none;align=center;verticalAlign=middle;rounded=0;fontSize=16;" value="D7 TB_PENGELUARAN_OPERASIONAL" vertex="1">
          <mxGeometry height="39.89" width="320" y="0.11" as="geometry" />
        </mxCell>
        <mxCell id="ysOjoahSiFBGGim9s-G7-250" edge="1" parent="ysOjoahSiFBGGim9s-G7-248" style="endArrow=none;html=1;rounded=0;fontSize=12;startSize=8;endSize=8;curved=1;entryX=1;entryY=0;entryDx=0;entryDy=0;" target="ysOjoahSiFBGGim9s-G7-249" value="">
          <mxGeometry height="50" relative="1" width="50" as="geometry">
            <mxPoint y="0.10966415352970148" as="sourcePoint" />
            <mxPoint x="217.5" y="0.10966415352970148" as="targetPoint" />
          </mxGeometry>
        </mxCell>
        <mxCell id="ysOjoahSiFBGGim9s-G7-251" edge="1" parent="ysOjoahSiFBGGim9s-G7-248" style="endArrow=none;html=1;rounded=0;fontSize=12;startSize=8;endSize=8;curved=1;entryX=1;entryY=1;entryDx=0;entryDy=0;" target="ysOjoahSiFBGGim9s-G7-249" value="">
          <mxGeometry height="50" relative="1" width="50" as="geometry">
            <mxPoint y="40" as="sourcePoint" />
            <mxPoint x="217.5" y="40" as="targetPoint" />
          </mxGeometry>
        </mxCell>
        <mxCell id="ysOjoahSiFBGGim9s-G7-253" edge="1" parent="1" source="ysOjoahSiFBGGim9s-G7-249" style="edgeStyle=orthogonalEdgeStyle;rounded=0;orthogonalLoop=1;jettySize=auto;html=1;entryX=0.938;entryY=0.761;entryDx=0;entryDy=0;entryPerimeter=0;" target="ysOjoahSiFBGGim9s-G7-173">
          <mxGeometry relative="1" as="geometry">
            <Array as="points">
              <mxPoint x="2770" y="1557" />
            </Array>
          </mxGeometry>
        </mxCell>
        <mxCell id="ysOjoahSiFBGGim9s-G7-254" connectable="0" parent="ysOjoahSiFBGGim9s-G7-253" style="edgeLabel;html=1;align=center;verticalAlign=middle;resizable=0;points=[];" value="Data pengeluaran" vertex="1">
          <mxGeometry relative="1" x="0.2667" as="geometry">
            <mxPoint as="offset" />
          </mxGeometry>
        </mxCell>
        <mxCell id="ysOjoahSiFBGGim9s-G7-255" edge="1" parent="1" source="ysOjoahSiFBGGim9s-G7-153" style="edgeStyle=orthogonalEdgeStyle;rounded=0;orthogonalLoop=1;jettySize=auto;html=1;fontSize=12;startSize=8;endSize=8;exitX=1;exitY=0.5;exitDx=0;exitDy=0;entryX=0.25;entryY=1;entryDx=0;entryDy=0;" target="ysOjoahSiFBGGim9s-G7-143">
          <mxGeometry relative="1" as="geometry">
            <Array as="points">
              <mxPoint x="2870" y="870" />
            </Array>
            <mxPoint x="2640" y="790" as="sourcePoint" />
            <mxPoint x="3010" y="860" as="targetPoint" />
          </mxGeometry>
        </mxCell>
        <mxCell id="Ql6GGfELSbdIJ28yt1BH-1" connectable="0" parent="ysOjoahSiFBGGim9s-G7-255" style="edgeLabel;html=1;align=center;verticalAlign=middle;resizable=0;points=[];fontSize=12;" value="Data paket dan portofolio" vertex="1">
          <mxGeometry relative="1" x="-0.6529" y="-1" as="geometry">
            <mxPoint x="29" y="-1" as="offset" />
          </mxGeometry>
        </mxCell>
        <mxCell id="ysOjoahSiFBGGim9s-G7-257" edge="1" parent="1" source="ysOjoahSiFBGGim9s-G7-143" style="edgeStyle=orthogonalEdgeStyle;rounded=0;orthogonalLoop=1;jettySize=auto;html=1;fontSize=12;startSize=8;endSize=8;exitX=0.25;exitY=0;exitDx=0;exitDy=0;" target="ysOjoahSiFBGGim9s-G7-187">
          <mxGeometry relative="1" as="geometry">
            <Array as="points">
              <mxPoint x="2870" y="380" />
            </Array>
            <mxPoint x="2920" y="380" as="sourcePoint" />
            <mxPoint x="2610" y="390" as="targetPoint" />
          </mxGeometry>
        </mxCell>
        <mxCell id="ysOjoahSiFBGGim9s-G7-258" connectable="0" parent="ysOjoahSiFBGGim9s-G7-257" style="edgeLabel;html=1;align=center;verticalAlign=middle;resizable=0;points=[];fontSize=12;" value="Registrasi / login" vertex="1">
          <mxGeometry relative="1" x="-0.2579" y="4" as="geometry">
            <mxPoint x="-55" y="-5" as="offset" />
          </mxGeometry>
        </mxCell>
        <mxCell id="ysOjoahSiFBGGim9s-G7-259" edge="1" parent="1" style="edgeStyle=orthogonalEdgeStyle;rounded=0;orthogonalLoop=1;jettySize=auto;html=1;fontSize=12;startSize=8;endSize=8;exitX=0.929;exitY=0.264;exitDx=0;exitDy=0;exitPerimeter=0;" target="ysOjoahSiFBGGim9s-G7-143">
          <mxGeometry relative="1" as="geometry">
            <Array as="points">
              <mxPoint x="2910" y="611" />
            </Array>
            <mxPoint x="2530.06" y="610.96" as="sourcePoint" />
            <mxPoint x="2900" y="424" as="targetPoint" />
          </mxGeometry>
        </mxCell>
        <mxCell id="ysOjoahSiFBGGim9s-G7-260" connectable="0" parent="ysOjoahSiFBGGim9s-G7-259" style="edgeLabel;html=1;align=center;verticalAlign=middle;resizable=0;points=[];fontSize=12;" value="Konfirmasi pemesanan dan status pemesanan" vertex="1">
          <mxGeometry relative="1" x="0.521" y="2" as="geometry">
            <mxPoint x="-189" y="38" as="offset" />
          </mxGeometry>
        </mxCell>
        <mxCell id="ysOjoahSiFBGGim9s-G7-261" edge="1" parent="1" source="ysOjoahSiFBGGim9s-G7-187" style="edgeStyle=orthogonalEdgeStyle;rounded=0;orthogonalLoop=1;jettySize=auto;html=1;fontSize=12;startSize=8;endSize=8;" target="ysOjoahSiFBGGim9s-G7-264">
          <mxGeometry relative="1" as="geometry">
            <Array as="points">
              <mxPoint x="2780" y="450" />
            </Array>
            <mxPoint x="2550" y="495.0012371134019" as="sourcePoint" />
            <mxPoint x="2780" y="480" as="targetPoint" />
          </mxGeometry>
        </mxCell>
        <mxCell id="ysOjoahSiFBGGim9s-G7-262" connectable="0" parent="ysOjoahSiFBGGim9s-G7-261" style="edgeLabel;html=1;align=center;verticalAlign=middle;resizable=0;points=[];fontSize=12;" value="Data user baru/ubah" vertex="1">
          <mxGeometry relative="1" x="-0.3636" y="2" as="geometry">
            <mxPoint x="24" y="2" as="offset" />
          </mxGeometry>
        </mxCell>
        <mxCell id="ysOjoahSiFBGGim9s-G7-263" connectable="0" parent="1" style="group;rotation=90;" value="" vertex="1">
          <mxGeometry height="30.082474226804038" width="110" x="2740" y="519.9987628865979" as="geometry" />
        </mxCell>
        <mxCell id="ysOjoahSiFBGGim9s-G7-264" parent="ysOjoahSiFBGGim9s-G7-263" style="text;html=1;whiteSpace=wrap;strokeColor=none;fillColor=none;align=center;verticalAlign=middle;rounded=0;fontSize=16;" value="D1 TB_USER" vertex="1">
          <mxGeometry height="30" width="110" y="0.08" as="geometry" />
        </mxCell>
        <mxCell id="ysOjoahSiFBGGim9s-G7-265" edge="1" parent="ysOjoahSiFBGGim9s-G7-263" style="endArrow=none;html=1;rounded=0;fontSize=12;startSize=8;endSize=8;curved=1;entryX=1;entryY=0;entryDx=0;entryDy=0;" target="ysOjoahSiFBGGim9s-G7-264" value="">
          <mxGeometry height="50" relative="1" width="50" as="geometry">
            <mxPoint y="0.08247422680403815" as="sourcePoint" />
            <mxPoint x="60" y="0.08247422680403815" as="targetPoint" />
          </mxGeometry>
        </mxCell>
        <mxCell id="ysOjoahSiFBGGim9s-G7-266" edge="1" parent="ysOjoahSiFBGGim9s-G7-263" style="endArrow=none;html=1;rounded=0;fontSize=12;startSize=8;endSize=8;curved=1;entryX=1;entryY=1;entryDx=0;entryDy=0;" target="ysOjoahSiFBGGim9s-G7-264" value="">
          <mxGeometry height="50" relative="1" width="50" as="geometry">
            <mxPoint y="30.082474226804038" as="sourcePoint" />
            <mxPoint x="60" y="30.082474226804038" as="targetPoint" />
          </mxGeometry>
        </mxCell>
        <mxCell id="ysOjoahSiFBGGim9s-G7-267" edge="1" parent="ysOjoahSiFBGGim9s-G7-263" source="ysOjoahSiFBGGim9s-G7-264" style="edgeStyle=none;curved=1;rounded=0;orthogonalLoop=1;jettySize=auto;html=1;fontSize=12;startSize=8;endSize=8;">
          <mxGeometry relative="1" as="geometry">
            <mxPoint x="40" as="targetPoint" />
          </mxGeometry>
        </mxCell>
        <mxCell id="ysOjoahSiFBGGim9s-G7-268" edge="1" parent="1" source="ysOjoahSiFBGGim9s-G7-264" style="edgeStyle=orthogonalEdgeStyle;rounded=0;orthogonalLoop=1;jettySize=auto;html=1;fontSize=12;startSize=8;endSize=8;exitX=0;exitY=0.5;exitDx=0;exitDy=0;entryX=0.5;entryY=1;entryDx=0;entryDy=0;" target="ysOjoahSiFBGGim9s-G7-187">
          <mxGeometry relative="1" as="geometry">
            <Array as="points">
              <mxPoint x="2480" y="535" />
            </Array>
            <mxPoint x="2699.93" y="580.0012371134019" as="sourcePoint" />
            <mxPoint x="2469.93" y="540" as="targetPoint" />
          </mxGeometry>
        </mxCell>
        <mxCell id="ysOjoahSiFBGGim9s-G7-269" connectable="0" parent="ysOjoahSiFBGGim9s-G7-268" style="edgeLabel;html=1;align=center;verticalAlign=middle;resizable=0;points=[];fontSize=12;" value="Data user" vertex="1">
          <mxGeometry relative="1" x="0.3588" as="geometry">
            <mxPoint x="114" as="offset" />
          </mxGeometry>
        </mxCell>
        <mxCell id="ysOjoahSiFBGGim9s-G7-270" edge="1" parent="1" source="ysOjoahSiFBGGim9s-G7-143" style="edgeStyle=orthogonalEdgeStyle;rounded=0;orthogonalLoop=1;jettySize=auto;html=1;entryX=1;entryY=0;entryDx=0;entryDy=0;fontSize=12;startSize=8;endSize=8;jumpStyle=arc;" target="ysOjoahSiFBGGim9s-G7-180">
          <mxGeometry relative="1" as="geometry">
            <Array as="points">
              <mxPoint x="2890" y="1060" />
              <mxPoint x="2530" y="1060" />
            </Array>
            <mxPoint x="2909" y="710" as="sourcePoint" />
            <mxPoint x="2530" y="969" as="targetPoint" />
          </mxGeometry>
        </mxCell>
        <mxCell id="ysOjoahSiFBGGim9s-G7-271" connectable="0" parent="ysOjoahSiFBGGim9s-G7-270" style="edgeLabel;html=1;align=center;verticalAlign=middle;resizable=0;points=[];fontSize=12;" value="Data pembayaran dan bukti bayar" vertex="1">
          <mxGeometry relative="1" x="0.5636" as="geometry">
            <mxPoint x="19" y="-1" as="offset" />
          </mxGeometry>
        </mxCell>
        <mxCell id="ysOjoahSiFBGGim9s-G7-272" edge="1" parent="1" source="mm8ewPxjDXuYCMIWR43z-1" style="edgeStyle=orthogonalEdgeStyle;rounded=0;orthogonalLoop=1;jettySize=auto;html=1;fontSize=12;startSize=8;endSize=8;exitX=1;exitY=0.5;exitDx=0;exitDy=0;">
          <mxGeometry relative="1" as="geometry">
            <Array as="points">
              <mxPoint x="3050" y="660" />
            </Array>
            <mxPoint x="2549.97" y="720" as="sourcePoint" />
            <mxPoint x="3050" y="910" as="targetPoint" />
          </mxGeometry>
        </mxCell>
        <mxCell id="ysOjoahSiFBGGim9s-G7-273" connectable="0" parent="ysOjoahSiFBGGim9s-G7-272" style="edgeLabel;html=1;align=center;verticalAlign=middle;resizable=0;points=[];fontSize=12;" value="Data pemesanan baru" vertex="1">
          <mxGeometry relative="1" x="-0.4814" y="1" as="geometry">
            <mxPoint x="-53" y="1" as="offset" />
          </mxGeometry>
        </mxCell>
        <mxCell id="ysOjoahSiFBGGim9s-G7-278" edge="1" parent="1" source="ysOjoahSiFBGGim9s-G7-153" style="edgeStyle=orthogonalEdgeStyle;rounded=0;orthogonalLoop=1;jettySize=auto;html=1;entryX=0.5;entryY=0;entryDx=0;entryDy=0;fontSize=12;startSize=8;endSize=8;exitX=0.5;exitY=0;exitDx=0;exitDy=0;" target="ysOjoahSiFBGGim9s-G7-281">
          <mxGeometry relative="1" as="geometry">
            <Array as="points">
              <mxPoint x="2480" y="770" />
              <mxPoint x="2800" y="770" />
            </Array>
            <mxPoint x="2530" y="800.06" as="sourcePoint" />
          </mxGeometry>
        </mxCell>
        <mxCell id="ysOjoahSiFBGGim9s-G7-279" connectable="0" parent="ysOjoahSiFBGGim9s-G7-278" style="edgeLabel;html=1;align=center;verticalAlign=middle;resizable=0;points=[];fontSize=12;" value="Data paket baru/ubah/hapus" vertex="1">
          <mxGeometry relative="1" x="-0.4127" y="3" as="geometry">
            <mxPoint x="86" as="offset" />
          </mxGeometry>
        </mxCell>
        <mxCell id="ysOjoahSiFBGGim9s-G7-280" connectable="0" parent="1" style="group;" value="" vertex="1">
          <mxGeometry height="30.082474226804038" width="120" x="2740" y="805" as="geometry" />
        </mxCell>
        <mxCell id="ysOjoahSiFBGGim9s-G7-281" parent="ysOjoahSiFBGGim9s-G7-280" style="text;html=1;whiteSpace=wrap;strokeColor=none;fillColor=none;align=center;verticalAlign=middle;rounded=0;fontSize=16;" value="D2 TB_PAKET" vertex="1">
          <mxGeometry height="30" width="120" y="0.08" as="geometry" />
        </mxCell>
        <mxCell id="ysOjoahSiFBGGim9s-G7-282" edge="1" parent="ysOjoahSiFBGGim9s-G7-280" style="endArrow=none;html=1;rounded=0;fontSize=12;startSize=8;endSize=8;curved=1;entryX=1;entryY=0;entryDx=0;entryDy=0;" target="ysOjoahSiFBGGim9s-G7-281" value="">
          <mxGeometry height="50" relative="1" width="50" as="geometry">
            <mxPoint y="0.08247422680403815" as="sourcePoint" />
            <mxPoint x="60" y="0.08247422680403815" as="targetPoint" />
          </mxGeometry>
        </mxCell>
        <mxCell id="ysOjoahSiFBGGim9s-G7-283" edge="1" parent="ysOjoahSiFBGGim9s-G7-280" style="endArrow=none;html=1;rounded=0;fontSize=12;startSize=8;endSize=8;curved=1;entryX=1;entryY=1;entryDx=0;entryDy=0;" target="ysOjoahSiFBGGim9s-G7-281" value="">
          <mxGeometry height="50" relative="1" width="50" as="geometry">
            <mxPoint y="30.082474226804038" as="sourcePoint" />
            <mxPoint x="60" y="30.082474226804038" as="targetPoint" />
          </mxGeometry>
        </mxCell>
        <mxCell id="ysOjoahSiFBGGim9s-G7-284" edge="1" parent="1" source="ysOjoahSiFBGGim9s-G7-281" style="edgeStyle=orthogonalEdgeStyle;rounded=0;orthogonalLoop=1;jettySize=auto;html=1;fontSize=12;startSize=8;endSize=8;entryX=1;entryY=0;entryDx=0;entryDy=0;exitX=0;exitY=0.5;exitDx=0;exitDy=0;" target="ysOjoahSiFBGGim9s-G7-153">
          <mxGeometry relative="1" as="geometry">
            <Array as="points">
              <mxPoint x="2635" y="820" />
            </Array>
            <mxPoint x="2730" y="820" as="sourcePoint" />
            <mxPoint x="2529.497474683061" y="819.502525316939" as="targetPoint" />
          </mxGeometry>
        </mxCell>
        <mxCell id="ysOjoahSiFBGGim9s-G7-285" connectable="0" parent="ysOjoahSiFBGGim9s-G7-284" style="edgeLabel;html=1;align=center;verticalAlign=middle;resizable=0;points=[];fontSize=12;" value="Data paket layanan" vertex="1">
          <mxGeometry relative="1" x="0.0386" as="geometry">
            <mxPoint x="12" as="offset" />
          </mxGeometry>
        </mxCell>
        <mxCell id="ysOjoahSiFBGGim9s-G7-286" edge="1" parent="1" source="ysOjoahSiFBGGim9s-G7-153" style="edgeStyle=orthogonalEdgeStyle;rounded=0;orthogonalLoop=1;jettySize=auto;html=1;fontSize=12;startSize=8;endSize=8;exitX=0.96;exitY=0.705;exitDx=0;exitDy=0;exitPerimeter=0;">
          <mxGeometry relative="1" as="geometry">
            <Array as="points">
              <mxPoint x="2544" y="900" />
              <mxPoint x="2780" y="900" />
              <mxPoint x="2780" y="940" />
            </Array>
            <mxPoint x="2564" y="900" as="sourcePoint" />
            <mxPoint x="2780" y="940" as="targetPoint" />
          </mxGeometry>
        </mxCell>
        <mxCell id="ysOjoahSiFBGGim9s-G7-287" connectable="0" parent="ysOjoahSiFBGGim9s-G7-286" style="edgeLabel;html=1;align=center;verticalAlign=middle;resizable=0;points=[];fontSize=12;" value="Data portofolio baru/ubah/hapus" vertex="1">
          <mxGeometry relative="1" x="-0.4441" y="-2" as="geometry">
            <mxPoint x="35" y="-5" as="offset" />
          </mxGeometry>
        </mxCell>
        <mxCell id="ysOjoahSiFBGGim9s-G7-288" connectable="0" parent="1" style="group;" value="" vertex="1">
          <mxGeometry height="30.08" width="170" x="2691" y="940" as="geometry" />
        </mxCell>
        <mxCell id="ysOjoahSiFBGGim9s-G7-289" parent="ysOjoahSiFBGGim9s-G7-288" style="text;html=1;whiteSpace=wrap;strokeColor=none;fillColor=none;align=center;verticalAlign=middle;rounded=0;fontSize=16;" value="D3 TB_PORTOFOLIO" vertex="1">
          <mxGeometry height="29.997532556545664" width="170" y="0.08246744345433552" as="geometry" />
        </mxCell>
        <mxCell id="ysOjoahSiFBGGim9s-G7-290" edge="1" parent="ysOjoahSiFBGGim9s-G7-288" style="endArrow=none;html=1;rounded=0;fontSize=12;startSize=8;endSize=8;curved=1;entryX=1;entryY=0;entryDx=0;entryDy=0;" target="ysOjoahSiFBGGim9s-G7-289" value="">
          <mxGeometry height="50" relative="1" width="50" as="geometry">
            <mxPoint y="0.08246744345433552" as="sourcePoint" />
            <mxPoint x="127.49999999999999" y="0.08246744345433552" as="targetPoint" />
          </mxGeometry>
        </mxCell>
        <mxCell id="ysOjoahSiFBGGim9s-G7-291" edge="1" parent="ysOjoahSiFBGGim9s-G7-288" style="endArrow=none;html=1;rounded=0;fontSize=12;startSize=8;endSize=8;curved=1;entryX=1;entryY=1;entryDx=0;entryDy=0;" target="ysOjoahSiFBGGim9s-G7-289" value="">
          <mxGeometry height="50" relative="1" width="50" as="geometry">
            <mxPoint y="30.08" as="sourcePoint" />
            <mxPoint x="127.49999999999999" y="30.08" as="targetPoint" />
          </mxGeometry>
        </mxCell>
        <mxCell id="ysOjoahSiFBGGim9s-G7-292" edge="1" parent="ysOjoahSiFBGGim9s-G7-288" source="ysOjoahSiFBGGim9s-G7-289" style="edgeStyle=none;curved=1;rounded=0;orthogonalLoop=1;jettySize=auto;html=1;exitX=0.5;exitY=0;exitDx=0;exitDy=0;fontSize=12;startSize=8;endSize=8;">
          <mxGeometry relative="1" as="geometry">
            <mxPoint x="85" as="targetPoint" />
          </mxGeometry>
        </mxCell>
        <mxCell id="ysOjoahSiFBGGim9s-G7-293" edge="1" parent="1" source="ysOjoahSiFBGGim9s-G7-289" style="edgeStyle=orthogonalEdgeStyle;rounded=0;orthogonalLoop=1;jettySize=auto;html=1;entryX=1;entryY=1;entryDx=0;entryDy=0;fontSize=12;startSize=8;endSize=8;" target="ysOjoahSiFBGGim9s-G7-153">
          <mxGeometry relative="1" as="geometry">
            <Array as="points">
              <mxPoint x="2761" y="920" />
              <mxPoint x="2550" y="920" />
            </Array>
            <mxPoint x="2550" y="919" as="targetPoint" />
          </mxGeometry>
        </mxCell>
        <mxCell id="ysOjoahSiFBGGim9s-G7-294" connectable="0" parent="ysOjoahSiFBGGim9s-G7-293" style="edgeLabel;html=1;align=center;verticalAlign=middle;resizable=0;points=[];fontSize=12;" value="Data portofolio" vertex="1">
          <mxGeometry relative="1" x="0.0549" as="geometry">
            <mxPoint x="2" as="offset" />
          </mxGeometry>
        </mxCell>
        <mxCell id="mm8ewPxjDXuYCMIWR43z-1" parent="1" style="ellipse;aspect=fixed;strokeWidth=2;whiteSpace=wrap;fixDash=0;" value="P2.0&#xa;Kelola Pemesanan" vertex="1">
          <mxGeometry height="140" width="140" x="2410" y="590" as="geometry" />
        </mxCell>
        <mxCell id="qRFkA4F6DMSVPhxs43NX-3" edge="1" parent="1" source="ysOjoahSiFBGGim9s-G7-140" style="edgeStyle=orthogonalEdgeStyle;rounded=0;orthogonalLoop=1;jettySize=auto;html=1;fontSize=12;startSize=8;endSize=8;entryX=-0.008;entryY=0.404;entryDx=0;entryDy=0;exitX=0.114;exitY=-0.02;exitDx=0;exitDy=0;exitPerimeter=0;entryPerimeter=0;" target="ysOjoahSiFBGGim9s-G7-187" value=" ">
          <mxGeometry relative="1" as="geometry">
            <Array as="points">
              <mxPoint x="2154" y="710" />
              <mxPoint x="2154" y="427" />
            </Array>
            <mxPoint x="2140" y="760" as="sourcePoint" />
            <mxPoint x="2052.76" y="934.96" as="targetPoint" />
          </mxGeometry>
        </mxCell>
        <mxCell id="eOQVe81tGfd8ieuptfEY-1" edge="1" parent="1" source="ysOjoahSiFBGGim9s-G7-187" style="edgeStyle=orthogonalEdgeStyle;rounded=0;orthogonalLoop=1;jettySize=auto;html=1;fontSize=12;startSize=8;endSize=8;" target="ysOjoahSiFBGGim9s-G7-140">
          <mxGeometry relative="1" as="geometry">
            <Array as="points">
              <mxPoint x="2170" y="460" />
            </Array>
            <mxPoint x="2424.48" y="460.08000000000004" as="sourcePoint" />
            <mxPoint x="2170" y="980" as="targetPoint" />
          </mxGeometry>
        </mxCell>
        <mxCell id="eOQVe81tGfd8ieuptfEY-2" connectable="0" parent="eOQVe81tGfd8ieuptfEY-1" style="edgeLabel;html=1;align=center;verticalAlign=middle;resizable=0;points=[];fontSize=12;" value="Hak akses Admin" vertex="1">
          <mxGeometry relative="1" x="0.2369" y="-1" as="geometry">
            <mxPoint x="111" y="-227" as="offset" />
          </mxGeometry>
        </mxCell>
        <mxCell id="eOQVe81tGfd8ieuptfEY-5" connectable="0" parent="1" style="edgeLabel;html=1;align=center;verticalAlign=middle;resizable=0;points=[];fontSize=12;" value="Autentikasi Admin" vertex="1">
          <mxGeometry x="2280" y="424" as="geometry" />
        </mxCell>
        <mxCell id="7BxfJpHoBJpbHPaKrdRW-1" edge="1" parent="1" style="edgeStyle=orthogonalEdgeStyle;rounded=0;orthogonalLoop=1;jettySize=auto;html=1;fontSize=12;startSize=8;endSize=8;entryX=0;entryY=0.5;entryDx=0;entryDy=0;" target="ysOjoahSiFBGGim9s-G7-143">
          <mxGeometry relative="1" as="geometry">
            <Array as="points" />
            <mxPoint x="2550" y="420" as="sourcePoint" />
            <mxPoint x="2781" y="490" as="targetPoint" />
          </mxGeometry>
        </mxCell>
        <mxCell id="7BxfJpHoBJpbHPaKrdRW-2" connectable="0" parent="7BxfJpHoBJpbHPaKrdRW-1" style="edgeLabel;html=1;align=center;verticalAlign=middle;resizable=0;points=[];fontSize=12;" value="Data kredensial user" vertex="1">
          <mxGeometry relative="1" x="-0.3636" y="2" as="geometry">
            <mxPoint x="48" as="offset" />
          </mxGeometry>
        </mxCell>
        <mxCell id="L4uXvajokN23W6CR2Y1d-6" edge="1" parent="1" source="ysOjoahSiFBGGim9s-G7-143" style="edgeStyle=orthogonalEdgeStyle;rounded=0;orthogonalLoop=1;jettySize=auto;html=1;fontSize=12;startSize=8;endSize=8;entryX=0.977;entryY=0.313;entryDx=0;entryDy=0;entryPerimeter=0;" target="mm8ewPxjDXuYCMIWR43z-1">
          <mxGeometry relative="1" as="geometry">
            <Array as="points">
              <mxPoint x="2930" y="634" />
            </Array>
            <mxPoint x="2949.96" y="435.68999999999994" as="sourcePoint" />
            <mxPoint x="2549.8974746830586" y="634.3925253169417" as="targetPoint" />
          </mxGeometry>
        </mxCell>
        <mxCell id="L4uXvajokN23W6CR2Y1d-7" connectable="0" parent="L4uXvajokN23W6CR2Y1d-6" style="edgeLabel;html=1;align=center;verticalAlign=middle;resizable=0;points=[];fontSize=12;" value="Ajuan pemesanan" vertex="1">
          <mxGeometry relative="1" x="0.3588" as="geometry">
            <mxPoint x="-12" y="-2" as="offset" />
          </mxGeometry>
        </mxCell>
        <mxCell id="L4uXvajokN23W6CR2Y1d-10" edge="1" parent="1" source="ysOjoahSiFBGGim9s-G7-199" style="edgeStyle=orthogonalEdgeStyle;rounded=0;orthogonalLoop=1;jettySize=auto;html=1;fontSize=12;startSize=8;endSize=8;entryX=1;entryY=0;entryDx=0;entryDy=0;">
          <mxGeometry relative="1" as="geometry">
            <Array as="points">
              <mxPoint x="2941" y="690" />
              <mxPoint x="2891" y="690" />
              <mxPoint x="2891" y="691" />
            </Array>
            <mxPoint x="2941" y="520" as="sourcePoint" />
            <mxPoint x="2540" y="691" as="targetPoint" />
          </mxGeometry>
        </mxCell>
        <mxCell id="L4uXvajokN23W6CR2Y1d-11" connectable="0" parent="L4uXvajokN23W6CR2Y1d-10" style="edgeLabel;html=1;align=center;verticalAlign=middle;resizable=0;points=[];fontSize=12;" value="Data pemesanan" vertex="1">
          <mxGeometry relative="1" x="0.3588" as="geometry">
            <mxPoint x="-39" y="-2" as="offset" />
          </mxGeometry>
        </mxCell>
      </root>
    </mxGraphModel>
  </diagram>
</mxfile>
